{
  "type": "Topology",
  "objects": {
    "collection": {
      "type": "GeometryCollection",
      "geometries": [
        {
          "type": "Polygon",
          "properties": {
            "kecamatan": "BANYUMANIK"
          },
          "arcs": [
            [
              0
            ]
          ]
        },
        {
          "type": "Polygon",
          "properties": {
            "kecamatan": "CANDISARI"
          },
          "arcs": [
            [
              1
            ]
          ]
        }
      ]
    }
  },
  "arcs": [
    [
      [
        0,
        9999
      ],
      [
        151,
        -6171
      ],
      [
        3958,
        -2108
      ],
      [
        1913,
        6774
      ],
      [
        -6022,
        1505
      ]
    ],
    [
      [
        6098,
        8580
      ],
      [
        -1932,
        -6881
      ],
      [
        2822,
        -1699
      ],
      [
        3011,
        7139
      ],
      [
        -3901,
        1441
      ]
    ]
  ],
  "transform": {
    "scale": [
      5.665391978636778e-7,
      4.956641988953834e-7
    ],
    "translate": [
      107.756427526474,
      -6.572410970516223
    ]
  },
  "bbox": [
    107.756427526474,
    -6.572410970516223,
    107.76209235191344,
    -6.567454824191468
  ]
}
